{
  "id": "la_serena_b7a9518631",
  "comuna": "la_serena",
  "ruta": "Ordenanzas Descargadas\\1-600\\la_serena_3988_ordenanza_sobre_de_derechos_municipales_por_permisos_concesiones_y_servicio__doc_34_3988_21102014031624.pdf",
  "nombre": "la_serena_3988_ordenanza_sobre_de_derechos_municipales_por_permisos_concesiones_y_servicio__doc_34_3988_21102014031624.pdf",
  "veredicto": "ESCANEADO",
  "paginas": 27,
  "estado": "HECHO",
  "sesion": "Ordenanzas S4",
  "inicio": "2026-07-15T08:25:42",
  "fin": "2026-07-15T08:26:22",
  "resultado": {
    "tiene_tablas": false,
    "rangos": [],
    "paginas_utiles": 0,
    "confianza": "MEDIA",
    "metodo": "",
    "nota": "Decreto 3988/2014 aprueba Ordenanza sobre Derechos Municipales por Permisos, Concesiones y Servicios: tablas de tarifas/montos por tramites municipales, no normas urbanisticas de zonificacion."
  }
}